{"nodes": [{"id": "resources_js_pages_kanban_board_tsx", "label": "Board.tsx", "file_type": "code", "source_file": "resources\\js\\pages\\Kanban\\Board.tsx", "source_location": "L1"}, {"id": "board_kanbanboardpage", "label": "KanbanBoardPage()", "file_type": "code", "source_file": "resources\\js\\pages\\Kanban\\Board.tsx", "source_location": "L20"}], "edges": [{"source": "resources_js_pages_kanban_board_tsx", "target": "board", "relation": "imports_from", "confidence": "EXTRACTED", "source_file": "resources\\js\\pages\\Kanban\\Board.tsx", "source_location": "L1", "weight": 1.0}, {"source": "resources_js_pages_kanban_board_tsx", "target": "button", "relation": "imports_from", "confidence": "EXTRACTED", "source_file": "resources\\js\\pages\\Kanban\\Board.tsx", "source_location": "L2", "weight": 1.0}, {"source": "resources_js_pages_kanban_board_tsx", "target": "dialog", "relation": "imports_from", "confidence": "EXTRACTED", "source_file": "resources\\js\\pages\\Kanban\\Board.tsx", "source_location": "L3", "weight": 1.0}, {"source": "resources_js_pages_kanban_board_tsx", "target": "input", "relation": "imports_from", "confidence": "EXTRACTED", "source_file": "resources\\js\\pages\\Kanban\\Board.tsx", "source_location": "L4", "weight": 1.0}, {"source": "resources_js_pages_kanban_board_tsx", "target": "label", "relation": "imports_from", "confidence": "EXTRACTED", "source_file": "resources\\js\\pages\\Kanban\\Board.tsx", "source_location": "L5", "weight": 1.0}, {"source": "resources_js_pages_kanban_board_tsx", "target": "textarea", "relation": "imports_from", "confidence": "EXTRACTED", "source_file": "resources\\js\\pages\\Kanban\\Board.tsx", "source_location": "L6", "weight": 1.0}, {"source": "resources_js_pages_kanban_board_tsx", "target": "app_layout", "relation": "imports_from", "confidence": "EXTRACTED", "source_file": "resources\\js\\pages\\Kanban\\Board.tsx", "source_location": "L7", "weight": 1.0}, {"source": "resources_js_pages_kanban_board_tsx", "target": "kanban", "relation": "imports_from", "confidence": "EXTRACTED", "source_file": "resources\\js\\pages\\Kanban\\Board.tsx", "source_location": "L8", "weight": 1.0}, {"source": "resources_js_pages_kanban_board_tsx", "target": "types", "relation": "imports_from", "confidence": "EXTRACTED", "source_file": "resources\\js\\pages\\Kanban\\Board.tsx", "source_location": "L9", "weight": 1.0}, {"source": "resources_js_pages_kanban_board_tsx", "target": "dnd", "relation": "imports_from", "confidence": "EXTRACTED", "source_file": "resources\\js\\pages\\Kanban\\Board.tsx", "source_location": "L10", "weight": 1.0}, {"source": "resources_js_pages_kanban_board_tsx", "target": "react", "relation": "imports_from", "confidence": "EXTRACTED", "source_file": "resources\\js\\pages\\Kanban\\Board.tsx", "source_location": "L11", "weight": 1.0}, {"source": "resources_js_pages_kanban_board_tsx", "target": "lucide_react", "relation": "imports_from", "confidence": "EXTRACTED", "source_file": "resources\\js\\pages\\Kanban\\Board.tsx", "source_location": "L12", "weight": 1.0}, {"source": "resources_js_pages_kanban_board_tsx", "target": "react", "relation": "imports_from", "confidence": "EXTRACTED", "source_file": "resources\\js\\pages\\Kanban\\Board.tsx", "source_location": "L13", "weight": 1.0}, {"source": "resources_js_pages_kanban_board_tsx", "target": "sonner", "relation": "imports_from", "confidence": "EXTRACTED", "source_file": "resources\\js\\pages\\Kanban\\Board.tsx", "source_location": "L14", "weight": 1.0}, {"source": "resources_js_pages_kanban_board_tsx", "target": "board_kanbanboardpage", "relation": "contains", "confidence": "EXTRACTED", "source_file": "resources\\js\\pages\\Kanban\\Board.tsx", "source_location": "L20", "weight": 1.0}], "raw_calls": [{"caller_nid": "board_kanbanboardpage", "callee": "useState", "source_file": "resources\\js\\pages\\Kanban\\Board.tsx", "source_location": "L21"}, {"caller_nid": "board_kanbanboardpage", "callee": "useState", "source_file": "resources\\js\\pages\\Kanban\\Board.tsx", "source_location": "L22"}, {"caller_nid": "board_kanbanboardpage", "callee": "useState", "source_file": "resources\\js\\pages\\Kanban\\Board.tsx", "source_location": "L23"}, {"caller_nid": "board_kanbanboardpage", "callee": "useEffect", "source_file": "resources\\js\\pages\\Kanban\\Board.tsx", "source_location": "L26"}, {"caller_nid": "board_kanbanboardpage", "callee": "useEffect", "source_file": "resources\\js\\pages\\Kanban\\Board.tsx", "source_location": "L31"}, {"caller_nid": "board_kanbanboardpage", "callee": "useForm", "source_file": "resources\\js\\pages\\Kanban\\Board.tsx", "source_location": "L102"}]}