{"nodes": [{"id": "app_http_controllers_admin_agendasettingcontroller_php", "label": "AgendaSettingController.php", "file_type": "code", "source_file": "app\\Http\\Controllers\\Admin\\AgendaSettingController.php", "source_location": "L1"}, {"id": "agendasettingcontroller_agendasettingcontroller", "label": "AgendaSettingController", "file_type": "code", "source_file": "app\\Http\\Controllers\\Admin\\AgendaSettingController.php", "source_location": "L12"}, {"id": "agendasettingcontroller_agendasettingcontroller_index", "label": ".index()", "file_type": "code", "source_file": "app\\Http\\Controllers\\Admin\\AgendaSettingController.php", "source_location": "L14"}, {"id": "agendasettingcontroller_agendasettingcontroller_store", "label": ".store()", "file_type": "code", "source_file": "app\\Http\\Controllers\\Admin\\AgendaSettingController.php", "source_location": "L58"}, {"id": "agendasettingcontroller_agendasettingcontroller_update", "label": ".update()", "file_type": "code", "source_file": "app\\Http\\Controllers\\Admin\\AgendaSettingController.php", "source_location": "L75"}, {"id": "agendasettingcontroller_agendasettingcontroller_destroy", "label": ".destroy()", "file_type": "code", "source_file": "app\\Http\\Controllers\\Admin\\AgendaSettingController.php", "source_location": "L94"}, {"id": "agendasettingcontroller_agendasettingcontroller_attachuser", "label": ".attachUser()", "file_type": "code", "source_file": "app\\Http\\Controllers\\Admin\\AgendaSettingController.php", "source_location": "L101"}, {"id": "agendasettingcontroller_agendasettingcontroller_detachuser", "label": ".detachUser()", "file_type": "code", "source_file": "app\\Http\\Controllers\\Admin\\AgendaSettingController.php", "source_location": "L113"}, {"id": "agendasettingcontroller_agendasettingcontroller_getinstancename", "label": ".getInstanceName()", "file_type": "code", "source_file": "app\\Http\\Controllers\\Admin\\AgendaSettingController.php", "source_location": "L122"}, {"id": "agendasettingcontroller_agendasettingcontroller_connectwhatsapp", "label": ".connectWhatsapp()", "file_type": "code", "source_file": "app\\Http\\Controllers\\Admin\\AgendaSettingController.php", "source_location": "L149"}, {"id": "agendasettingcontroller_agendasettingcontroller_checkwhatsappstatus", "label": ".checkWhatsappStatus()", "file_type": "code", "source_file": "app\\Http\\Controllers\\Admin\\AgendaSettingController.php", "source_location": "L163"}, {"id": "agendasettingcontroller_agendasettingcontroller_disconnectwhatsapp", "label": ".disconnectWhatsapp()", "file_type": "code", "source_file": "app\\Http\\Controllers\\Admin\\AgendaSettingController.php", "source_location": "L175"}], "edges": [{"source": "app_http_controllers_admin_agendasettingcontroller_php", "target": "controller", "relation": "imports", "confidence": "EXTRACTED", "source_file": "app\\Http\\Controllers\\Admin\\AgendaSettingController.php", "source_location": "L5", "weight": 1.0}, {"source": "app_http_controllers_admin_agendasettingcontroller_php", "target": "channel", "relation": "imports", "confidence": "EXTRACTED", "source_file": "app\\Http\\Controllers\\Admin\\AgendaSettingController.php", "source_location": "L6", "weight": 1.0}, {"source": "app_http_controllers_admin_agendasettingcontroller_php", "target": "classroom", "relation": "imports", "confidence": "EXTRACTED", "source_file": "app\\Http\\Controllers\\Admin\\AgendaSettingController.php", "source_location": "L7", "weight": 1.0}, {"source": "app_http_controllers_admin_agendasettingcontroller_php", "target": "user", "relation": "imports", "confidence": "EXTRACTED", "source_file": "app\\Http\\Controllers\\Admin\\AgendaSettingController.php", "source_location": "L8", "weight": 1.0}, {"source": "app_http_controllers_admin_agendasettingcontroller_php", "target": "request", "relation": "imports", "confidence": "EXTRACTED", "source_file": "app\\Http\\Controllers\\Admin\\AgendaSettingController.php", "source_location": "L9", "weight": 1.0}, {"source": "app_http_controllers_admin_agendasettingcontroller_php", "target": "inertia", "relation": "imports", "confidence": "EXTRACTED", "source_file": "app\\Http\\Controllers\\Admin\\AgendaSettingController.php", "source_location": "L10", "weight": 1.0}, {"source": "app_http_controllers_admin_agendasettingcontroller_php", "target": "agendasettingcontroller_agendasettingcontroller", "relation": "contains", "confidence": "EXTRACTED", "source_file": "app\\Http\\Controllers\\Admin\\AgendaSettingController.php", "source_location": "L12", "weight": 1.0}, {"source": "agendasettingcontroller_agendasettingcontroller", "target": "agendasettingcontroller_agendasettingcontroller_index", "relation": "method", "confidence": "EXTRACTED", "source_file": "app\\Http\\Controllers\\Admin\\AgendaSettingController.php", "source_location": "L14", "weight": 1.0}, {"source": "agendasettingcontroller_agendasettingcontroller", "target": "agendasettingcontroller_agendasettingcontroller_store", "relation": "method", "confidence": "EXTRACTED", "source_file": "app\\Http\\Controllers\\Admin\\AgendaSettingController.php", "source_location": "L58", "weight": 1.0}, {"source": "agendasettingcontroller_agendasettingcontroller", "target": "agendasettingcontroller_agendasettingcontroller_update", "relation": "method", "confidence": "EXTRACTED", "source_file": "app\\Http\\Controllers\\Admin\\AgendaSettingController.php", "source_location": "L75", "weight": 1.0}, {"source": "agendasettingcontroller_agendasettingcontroller", "target": "agendasettingcontroller_agendasettingcontroller_destroy", "relation": "method", "confidence": "EXTRACTED", "source_file": "app\\Http\\Controllers\\Admin\\AgendaSettingController.php", "source_location": "L94", "weight": 1.0}, {"source": "agendasettingcontroller_agendasettingcontroller", "target": "agendasettingcontroller_agendasettingcontroller_attachuser", "relation": "method", "confidence": "EXTRACTED", "source_file": "app\\Http\\Controllers\\Admin\\AgendaSettingController.php", "source_location": "L101", "weight": 1.0}, {"source": "agendasettingcontroller_agendasettingcontroller", "target": "agendasettingcontroller_agendasettingcontroller_detachuser", "relation": "method", "confidence": "EXTRACTED", "source_file": "app\\Http\\Controllers\\Admin\\AgendaSettingController.php", "source_location": "L113", "weight": 1.0}, {"source": "agendasettingcontroller_agendasettingcontroller", "target": "agendasettingcontroller_agendasettingcontroller_getinstancename", "relation": "method", "confidence": "EXTRACTED", "source_file": "app\\Http\\Controllers\\Admin\\AgendaSettingController.php", "source_location": "L122", "weight": 1.0}, {"source": "agendasettingcontroller_agendasettingcontroller", "target": "agendasettingcontroller_agendasettingcontroller_connectwhatsapp", "relation": "method", "confidence": "EXTRACTED", "source_file": "app\\Http\\Controllers\\Admin\\AgendaSettingController.php", "source_location": "L149", "weight": 1.0}, {"source": "agendasettingcontroller_agendasettingcontroller", "target": "agendasettingcontroller_agendasettingcontroller_checkwhatsappstatus", "relation": "method", "confidence": "EXTRACTED", "source_file": "app\\Http\\Controllers\\Admin\\AgendaSettingController.php", "source_location": "L163", "weight": 1.0}, {"source": "agendasettingcontroller_agendasettingcontroller", "target": "agendasettingcontroller_agendasettingcontroller_disconnectwhatsapp", "relation": "method", "confidence": "EXTRACTED", "source_file": "app\\Http\\Controllers\\Admin\\AgendaSettingController.php", "source_location": "L175", "weight": 1.0}, {"source": "agendasettingcontroller_agendasettingcontroller_update", "target": "agendasettingcontroller_agendasettingcontroller_store", "relation": "calls", "confidence": "EXTRACTED", "source_file": "app\\Http\\Controllers\\Admin\\AgendaSettingController.php", "source_location": "L85", "weight": 1.0}, {"source": "agendasettingcontroller_agendasettingcontroller_connectwhatsapp", "target": "agendasettingcontroller_agendasettingcontroller_getinstancename", "relation": "calls", "confidence": "EXTRACTED", "source_file": "app\\Http\\Controllers\\Admin\\AgendaSettingController.php", "source_location": "L151", "weight": 1.0}, {"source": "agendasettingcontroller_agendasettingcontroller_checkwhatsappstatus", "target": "agendasettingcontroller_agendasettingcontroller_getinstancename", "relation": "calls", "confidence": "EXTRACTED", "source_file": "app\\Http\\Controllers\\Admin\\AgendaSettingController.php", "source_location": "L165", "weight": 1.0}, {"source": "agendasettingcontroller_agendasettingcontroller_disconnectwhatsapp", "target": "agendasettingcontroller_agendasettingcontroller_getinstancename", "relation": "calls", "confidence": "EXTRACTED", "source_file": "app\\Http\\Controllers\\Admin\\AgendaSettingController.php", "source_location": "L177", "weight": 1.0}], "raw_calls": [{"caller_nid": "agendasettingcontroller_agendasettingcontroller_index", "callee": "get", "source_file": "app\\Http\\Controllers\\Admin\\AgendaSettingController.php", "source_location": "L18"}, {"caller_nid": "agendasettingcontroller_agendasettingcontroller_index", "callee": "with", "source_file": "app\\Http\\Controllers\\Admin\\AgendaSettingController.php", "source_location": "L18"}, {"caller_nid": "agendasettingcontroller_agendasettingcontroller_index", "callee": "whereNull", "source_file": "app\\Http\\Controllers\\Admin\\AgendaSettingController.php", "source_location": "L18"}, {"caller_nid": "agendasettingcontroller_agendasettingcontroller_index", "callee": "Channel", "source_file": "app\\Http\\Controllers\\Admin\\AgendaSettingController.php", "source_location": "L18"}, {"caller_nid": "agendasettingcontroller_agendasettingcontroller_index", "callee": "get", "source_file": "app\\Http\\Controllers\\Admin\\AgendaSettingController.php", "source_location": "L25"}, {"caller_nid": "agendasettingcontroller_agendasettingcontroller_index", "callee": "with", "source_file": "app\\Http\\Controllers\\Admin\\AgendaSettingController.php", "source_location": "L25"}, {"caller_nid": "agendasettingcontroller_agendasettingcontroller_index", "callee": "Channel", "source_file": "app\\Http\\Controllers\\Admin\\AgendaSettingController.php", "source_location": "L25"}, {"caller_nid": "agendasettingcontroller_agendasettingcontroller_index", "callee": "map", "source_file": "app\\Http\\Controllers\\Admin\\AgendaSettingController.php", "source_location": "L33"}, {"caller_nid": "agendasettingcontroller_agendasettingcontroller_index", "callee": "get", "source_file": "app\\Http\\Controllers\\Admin\\AgendaSettingController.php", "source_location": "L33"}, {"caller_nid": "agendasettingcontroller_agendasettingcontroller_index", "callee": "ClassRoom", "source_file": "app\\Http\\Controllers\\Admin\\AgendaSettingController.php", "source_location": "L33"}, {"caller_nid": "agendasettingcontroller_agendasettingcontroller_index", "callee": "map", "source_file": "app\\Http\\Controllers\\Admin\\AgendaSettingController.php", "source_location": "L43"}, {"caller_nid": "agendasettingcontroller_agendasettingcontroller_index", "callee": "get", "source_file": "app\\Http\\Controllers\\Admin\\AgendaSettingController.php", "source_location": "L49"}, {"caller_nid": "agendasettingcontroller_agendasettingcontroller_index", "callee": "User", "source_file": "app\\Http\\Controllers\\Admin\\AgendaSettingController.php", "source_location": "L49"}, {"caller_nid": "agendasettingcontroller_agendasettingcontroller_index", "callee": "Inertia", "source_file": "app\\Http\\Controllers\\Admin\\AgendaSettingController.php", "source_location": "L51"}, {"caller_nid": "agendasettingcontroller_agendasettingcontroller_store", "callee": "validate", "source_file": "app\\Http\\Controllers\\Admin\\AgendaSettingController.php", "source_location": "L60"}, {"caller_nid": "agendasettingcontroller_agendasettingcontroller_store", "callee": "Channel", "source_file": "app\\Http\\Controllers\\Admin\\AgendaSettingController.php", "source_location": "L65"}, {"caller_nid": "agendasettingcontroller_agendasettingcontroller_store", "callee": "with", "source_file": "app\\Http\\Controllers\\Admin\\AgendaSettingController.php", "source_location": "L72"}, {"caller_nid": "agendasettingcontroller_agendasettingcontroller_store", "callee": "back", "source_file": "app\\Http\\Controllers\\Admin\\AgendaSettingController.php", "source_location": "L72"}, {"caller_nid": "agendasettingcontroller_agendasettingcontroller_update", "callee": "validate", "source_file": "app\\Http\\Controllers\\Admin\\AgendaSettingController.php", "source_location": "L77"}, {"caller_nid": "agendasettingcontroller_agendasettingcontroller_update", "callee": "hasFile", "source_file": "app\\Http\\Controllers\\Admin\\AgendaSettingController.php", "source_location": "L84"}, {"caller_nid": "agendasettingcontroller_agendasettingcontroller_update", "callee": "file", "source_file": "app\\Http\\Controllers\\Admin\\AgendaSettingController.php", "source_location": "L85"}, {"caller_nid": "agendasettingcontroller_agendasettingcontroller_update", "callee": "asset", "source_file": "app\\Http\\Controllers\\Admin\\AgendaSettingController.php", "source_location": "L86"}, {"caller_nid": "agendasettingcontroller_agendasettingcontroller_update", "callee": "with", "source_file": "app\\Http\\Controllers\\Admin\\AgendaSettingController.php", "source_location": "L91"}, {"caller_nid": "agendasettingcontroller_agendasettingcontroller_update", "callee": "back", "source_file": "app\\Http\\Controllers\\Admin\\AgendaSettingController.php", "source_location": "L91"}, {"caller_nid": "agendasettingcontroller_agendasettingcontroller_destroy", "callee": "delete", "source_file": "app\\Http\\Controllers\\Admin\\AgendaSettingController.php", "source_location": "L96"}, {"caller_nid": "agendasettingcontroller_agendasettingcontroller_destroy", "callee": "with", "source_file": "app\\Http\\Controllers\\Admin\\AgendaSettingController.php", "source_location": "L97"}, {"caller_nid": "agendasettingcontroller_agendasettingcontroller_destroy", "callee": "back", "source_file": "app\\Http\\Controllers\\Admin\\AgendaSettingController.php", "source_location": "L97"}, {"caller_nid": "agendasettingcontroller_agendasettingcontroller_attachuser", "callee": "validate", "source_file": "app\\Http\\Controllers\\Admin\\AgendaSettingController.php", "source_location": "L103"}, {"caller_nid": "agendasettingcontroller_agendasettingcontroller_attachuser", "callee": "syncWithoutDetaching", "source_file": "app\\Http\\Controllers\\Admin\\AgendaSettingController.php", "source_location": "L107"}, {"caller_nid": "agendasettingcontroller_agendasettingcontroller_attachuser", "callee": "speakers", "source_file": "app\\Http\\Controllers\\Admin\\AgendaSettingController.php", "source_location": "L107"}, {"caller_nid": "agendasettingcontroller_agendasettingcontroller_attachuser", "callee": "with", "source_file": "app\\Http\\Controllers\\Admin\\AgendaSettingController.php", "source_location": "L109"}, {"caller_nid": "agendasettingcontroller_agendasettingcontroller_attachuser", "callee": "back", "source_file": "app\\Http\\Controllers\\Admin\\AgendaSettingController.php", "source_location": "L109"}, {"caller_nid": "agendasettingcontroller_agendasettingcontroller_detachuser", "callee": "detach", "source_file": "app\\Http\\Controllers\\Admin\\AgendaSettingController.php", "source_location": "L115"}, {"caller_nid": "agendasettingcontroller_agendasettingcontroller_detachuser", "callee": "speakers", "source_file": "app\\Http\\Controllers\\Admin\\AgendaSettingController.php", "source_location": "L115"}, {"caller_nid": "agendasettingcontroller_agendasettingcontroller_detachuser", "callee": "with", "source_file": "app\\Http\\Controllers\\Admin\\AgendaSettingController.php", "source_location": "L116"}, {"caller_nid": "agendasettingcontroller_agendasettingcontroller_detachuser", "callee": "back", "source_file": "app\\Http\\Controllers\\Admin\\AgendaSettingController.php", "source_location": "L116"}, {"caller_nid": "agendasettingcontroller_agendasettingcontroller_getinstancename", "callee": "first", "source_file": "app\\Http\\Controllers\\Admin\\AgendaSettingController.php", "source_location": "L125"}, {"caller_nid": "agendasettingcontroller_agendasettingcontroller_getinstancename", "callee": "\\App\\Models\\Setting", "source_file": "app\\Http\\Controllers\\Admin\\AgendaSettingController.php", "source_location": "L125"}, {"caller_nid": "agendasettingcontroller_agendasettingcontroller_getinstancename", "callee": "value", "source_file": "app\\Http\\Controllers\\Admin\\AgendaSettingController.php", "source_location": "L132"}, {"caller_nid": "agendasettingcontroller_agendasettingcontroller_getinstancename", "callee": "\\App\\Models\\Setting", "source_file": "app\\Http\\Controllers\\Admin\\AgendaSettingController.php", "source_location": "L132"}, {"caller_nid": "agendasettingcontroller_agendasettingcontroller_getinstancename", "callee": "\\Illuminate\\Support\\Str", "source_file": "app\\Http\\Controllers\\Admin\\AgendaSettingController.php", "source_location": "L133"}, {"caller_nid": "agendasettingcontroller_agendasettingcontroller_getinstancename", "callee": "substr", "source_file": "app\\Http\\Controllers\\Admin\\AgendaSettingController.php", "source_location": "L136"}, {"caller_nid": "agendasettingcontroller_agendasettingcontroller_getinstancename", "callee": "uniqid", "source_file": "app\\Http\\Controllers\\Admin\\AgendaSettingController.php", "source_location": "L136"}, {"caller_nid": "agendasettingcontroller_agendasettingcontroller_getinstancename", "callee": "\\App\\Models\\Setting", "source_file": "app\\Http\\Controllers\\Admin\\AgendaSettingController.php", "source_location": "L138"}, {"caller_nid": "agendasettingcontroller_agendasettingcontroller_connectwhatsapp", "callee": "connectInstance", "source_file": "app\\Http\\Controllers\\Admin\\AgendaSettingController.php", "source_location": "L152"}, {"caller_nid": "agendasettingcontroller_agendasettingcontroller_connectwhatsapp", "callee": "json", "source_file": "app\\Http\\Controllers\\Admin\\AgendaSettingController.php", "source_location": "L157"}, {"caller_nid": "agendasettingcontroller_agendasettingcontroller_connectwhatsapp", "callee": "response", "source_file": "app\\Http\\Controllers\\Admin\\AgendaSettingController.php", "source_location": "L157"}, {"caller_nid": "agendasettingcontroller_agendasettingcontroller_checkwhatsappstatus", "callee": "getConnectionState", "source_file": "app\\Http\\Controllers\\Admin\\AgendaSettingController.php", "source_location": "L166"}, {"caller_nid": "agendasettingcontroller_agendasettingcontroller_checkwhatsappstatus", "callee": "json", "source_file": "app\\Http\\Controllers\\Admin\\AgendaSettingController.php", "source_location": "L169"}, {"caller_nid": "agendasettingcontroller_agendasettingcontroller_checkwhatsappstatus", "callee": "response", "source_file": "app\\Http\\Controllers\\Admin\\AgendaSettingController.php", "source_location": "L169"}, {"caller_nid": "agendasettingcontroller_agendasettingcontroller_disconnectwhatsapp", "callee": "logoutInstance", "source_file": "app\\Http\\Controllers\\Admin\\AgendaSettingController.php", "source_location": "L178"}, {"caller_nid": "agendasettingcontroller_agendasettingcontroller_disconnectwhatsapp", "callee": "with", "source_file": "app\\Http\\Controllers\\Admin\\AgendaSettingController.php", "source_location": "L179"}, {"caller_nid": "agendasettingcontroller_agendasettingcontroller_disconnectwhatsapp", "callee": "back", "source_file": "app\\Http\\Controllers\\Admin\\AgendaSettingController.php", "source_location": "L179"}]}