{"nodes": [{"id": "app_models_classschedule_php", "label": "ClassSchedule.php", "file_type": "code", "source_file": "app\\Models\\ClassSchedule.php", "source_location": "L1"}, {"id": "classschedule_classschedule", "label": "ClassSchedule", "file_type": "code", "source_file": "app\\Models\\ClassSchedule.php", "source_location": "L7"}, {"id": "classschedule_classschedule_classroom", "label": ".classRoom()", "file_type": "code", "source_file": "app\\Models\\ClassSchedule.php", "source_location": "L17"}, {"id": "classschedule_classschedule_subject", "label": ".subject()", "file_type": "code", "source_file": "app\\Models\\ClassSchedule.php", "source_location": "L22"}], "edges": [{"source": "app_models_classschedule_php", "target": "model", "relation": "imports", "confidence": "EXTRACTED", "source_file": "app\\Models\\ClassSchedule.php", "source_location": "L5", "weight": 1.0}, {"source": "app_models_classschedule_php", "target": "classschedule_classschedule", "relation": "contains", "confidence": "EXTRACTED", "source_file": "app\\Models\\ClassSchedule.php", "source_location": "L7", "weight": 1.0}, {"source": "classschedule_classschedule", "target": "classschedule_classschedule_classroom", "relation": "method", "confidence": "EXTRACTED", "source_file": "app\\Models\\ClassSchedule.php", "source_location": "L17", "weight": 1.0}, {"source": "classschedule_classschedule", "target": "classschedule_classschedule_subject", "relation": "method", "confidence": "EXTRACTED", "source_file": "app\\Models\\ClassSchedule.php", "source_location": "L22", "weight": 1.0}], "raw_calls": [{"caller_nid": "classschedule_classschedule_classroom", "callee": "belongsTo", "source_file": "app\\Models\\ClassSchedule.php", "source_location": "L19"}, {"caller_nid": "classschedule_classschedule_subject", "callee": "belongsTo", "source_file": "app\\Models\\ClassSchedule.php", "source_location": "L24"}]}